{
  "electronicAccessRelationships": [
    {
      "id": "5bfe1b7b-f151-4501-8cfa-23b321d5cd1e",
      "name": "Related resource",
      "source": "folio",
      "metadata": {
        "createdDate": "2026-04-02T09:40:32.994+00:00",
        "updatedDate": "2026-04-07T14:09:56.225+00:00",
        "updatedByUserId": "d2641676-7c58-4b29-b714-7f6436210f96"
      }
    },
    {
      "id": "ef03d582-219c-4221-8635-bc92f1107021",
      "name": "No display constant generated",
      "source": "folio",
      "metadata": {
        "createdDate": "2026-04-02T09:40:32.994+00:00",
        "updatedDate": "2026-04-07T14:09:56.207+00:00",
        "updatedByUserId": "d2641676-7c58-4b29-b714-7f6436210f96"
      }
    },
    {
      "id": "f50c90c9-bae0-4add-9cd0-db9092dbc9dd",
      "name": "No information provided",
      "source": "folio",
      "metadata": {
        "createdDate": "2026-04-02T09:40:32.994+00:00",
        "updatedDate": "2026-04-07T14:09:56.170+00:00",
        "updatedByUserId": "d2641676-7c58-4b29-b714-7f6436210f96"
      }
    },
    {
      "id": "f5d0068e-6272-458e-8a81-b85e7b9a14aa",
      "name": "Resource",
      "source": "folio",
      "metadata": {
        "createdDate": "2026-04-02T09:40:32.992+00:00",
        "updatedDate": "2026-04-07T14:09:56.147+00:00",
        "updatedByUserId": "d2641676-7c58-4b29-b714-7f6436210f96"
      }
    },
    {
      "id": "3b430592-2e09-4b48-9a0c-0636d66b9fb3",
      "name": "Version of resource",
      "source": "folio",
      "metadata": {
        "createdDate": "2026-04-02T09:40:32.994+00:00",
        "updatedDate": "2026-04-07T14:09:56.189+00:00",
        "updatedByUserId": "d2641676-7c58-4b29-b714-7f6436210f96"
      }
    }
  ],
  "totalRecords": 5
}
